Dflipflop/dff.v
module dff (
    input D,clk,
    output reg Q,Qn
);
    always @(posedge clk) begin
        Q<=D;
        Qn<= ~D;
    end
endmodule

Dflipflop/dff_tb.v
`timescale 1ns/1ns
`include "dff.v"

module dff_tb;
    reg clk,D;
    wire Q,Qn;

    dff uut(.clk(clk),.D(D),.Q(Q),.Qn(Qn));

    initial begin
        $dumpfile("dff.vcd");
        $dumpvars(0,dff_tb);
        clk=0;
        forever begin
            #5 clk=~clk;
        end
    end
    
    initial begin
        $monitor("clk=%0t, D=%d, Q=%d, Qn=%d",$time,D,Q,Qn);

        D=0;

        #10 D=1;
        #10 D=0;
        #10 D=1;
        #10 D=0;
        #10 D=1;

        #25 $finish;
    end
endmodule

Dflipflop/dff.vcd
$date
	Tue Oct 08 19:06:53 2024
$end
$version
	Icarus Verilog
$end
$timescale
	1ns
$end
$scope module dff_tb $end
$var wire 1 ! Qn $end
$var wire 1 " Q $end
$var reg 1 # D $end
$var reg 1 $ clk $end
$scope module uut $end
$var wire 1 # D $end
$var wire 1 $ clk $end
$var reg 1 " Q $end
$var reg 1 ! Qn $end
$upscope $end
$upscope $end
$enddefinitions $end
$comment Show the parameter values. $end
$dumpall
$end
#0
$dumpvars
0$
0#
x"
x!
$end
#5
1!
0"
1$
#10
0$
1#
#15
0!
1"
1$
#20
0$
0#
#25
1!
0"
1$
#30
0$
1#
#35
0!
1"
1$
#40
0$
0#
#45
1!
0"
1$
#50
0$
1#
#55
0!
1"
1$
