3_bit_syn_updown_counter/bit3sc.v
module jk (
    input J,K,clk,rst,
    output reg Q,Qn
);
    always @(posedge clk ) begin
        if (rst) begin
            Q=0;
            Qn=1;
        end else begin
            case ({J,K})
            2'b00:
                begin
                    Q=Q;
                    Qn=~Q;
                end
            2'b01: 
                begin
                    Q=0;
                    Qn=~Q;
                end    
            2'b10:
                begin
                    Q=1;
                    Qn=~Q;
                end 
            2'b11:
                begin
                    Q= ~Q;
                    Qn=~Q;
                end 
        endcase
        end
    end
endmodule

module bit3sc (
    input clk,
    input rst,
    input up_down,
    output [2:0] count
);

    wire [2:0] j, k;
    wire [2:0] q;
    wire l;

    jk f0 (.clk(clk), .rst(rst), .J(j[0]), .K(k[0]), .Q(q[0]));
    jk f1 (.clk(clk), .rst(rst), .J(j[1]), .K(k[1]), .Q(q[1]));
    jk f2 (.clk(clk), .rst(rst), .J(j[2]), .K(k[2]), .Q(q[2]));


    assign count = q;

    assign j[0] = 1;
    assign k[0] = 1;

    assign j[1] = (count[0] ~^ up_down);
    assign k[1] = (count[0] ~^ up_down);

    assign l=(~count[1]&~count[0]&~up_down)|(count[1]&count[0]&up_down);

    assign j[2] = l;
    assign k[2] = l;

endmodule

3_bit_syn_updown_counter/bit3sc_tb.v
`timescale 1ns / 1ns
`include "bit3sc.v"

module bit3sc_tb;
    reg clk;
    reg rst;
    reg up_down;
    wire [2:0] count; 

    bit3sc uut (
        .clk(clk),.rst(rst),.up_down(up_down),.count(count)
    );

    initial begin
        $dumpfile("bit3sc.vcd");
        $dumpvars(0,bit3sc_tb);
        clk = 0;
        forever #5 clk = ~clk;
    end

    initial begin

        rst = 1;
        up_down = 0;
        #10;
        
        rst = 0;
        #10;

        up_down = 1;
        #90;
        
        up_down = 0;
        #50;
        
        $finish;
    end

    initial begin
        $monitor("Time: %0t | rst: %b | Up/Down: %b | Count: %b", $time, rst, up_down, count);
    end

endmodule

3_bit_syn_updown_counter/bit3sc.vcd
$date
	Mon Oct 21 15:42:24 2024
$end
$version
	Icarus Verilog
$end
$timescale
	1ns
$end
$scope module bit3sc_tb $end
$var wire 3 ! count [2:0] $end
$var reg 1 " clk $end
$var reg 1 # rst $end
$var reg 1 $ up_down $end
$scope module uut $end
$var wire 1 " clk $end
$var wire 3 % count [2:0] $end
$var wire 1 & l $end
$var wire 1 # rst $end
$var wire 1 $ up_down $end
$var wire 3 ' q [2:0] $end
$var wire 3 ( k [2:0] $end
$var wire 3 ) j [2:0] $end
$scope module f0 $end
$var wire 1 * J $end
$var wire 1 + K $end
$var wire 1 " clk $end
$var wire 1 # rst $end
$var reg 1 , Q $end
$var reg 1 - Qn $end
$upscope $end
$scope module f1 $end
$var wire 1 . J $end
$var wire 1 / K $end
$var wire 1 " clk $end
$var wire 1 # rst $end
$var reg 1 0 Q $end
$var reg 1 1 Qn $end
$upscope $end
$scope module f2 $end
$var wire 1 2 J $end
$var wire 1 3 K $end
$var wire 1 " clk $end
$var wire 1 # rst $end
$var reg 1 4 Q $end
$var reg 1 5 Qn $end
$upscope $end
$upscope $end
$upscope $end
$enddefinitions $end
$comment Show the parameter values. $end
$dumpall
$end
#0
$dumpvars
x5
x4
x3
x2
x1
x0
x/
x.
x-
x,
1+
1*
bx1 )
bx1 (
bx '
x&
bx %
0$
1#
0"
bx !
$end
#5
12
13
1&
1.
1/
b111 )
b111 (
1-
0,
11
00
15
b0 !
b0 %
b0 '
04
1"
#10
0"
0#
#15
02
03
0&
0.
0/
b1 )
b1 (
05
14
01
10
0-
b111 !
b111 %
b111 '
1,
1"
#20
12
13
1.
1/
1&
b111 )
b111 (
0"
1$
#25
02
03
0&
0.
0/
b1 )
b1 (
1-
0,
11
00
15
b0 !
b0 %
b0 '
04
1"
#30
0"
#35
1.
1/
b11 )
b11 (
0-
b1 !
b1 %
b1 '
1,
1"
#40
0"
#45
0.
0/
b1 )
b1 (
1-
0,
01
b10 !
b10 %
b10 '
10
1"
#50
0"
#55
12
13
1&
1.
1/
b111 )
b111 (
0-
b11 !
b11 %
b11 '
1,
1"
#60
0"
#65
02
03
0&
0.
0/
b1 )
b1 (
1-
0,
11
00
05
b100 !
b100 %
b100 '
14
1"
#70
0"
#75
1.
1/
b11 )
b11 (
0-
b101 !
b101 %
b101 '
1,
1"
#80
0"
#85
0.
0/
b1 )
b1 (
1-
0,
01
b110 !
b110 %
b110 '
10
1"
#90
0"
#95
12
13
1&
1.
1/
b111 )
b111 (
0-
b111 !
b111 %
b111 '
1,
1"
#100
0"
#105
02
03
0&
0.
0/
b1 )
b1 (
1-
0,
11
00
15
b0 !
b0 %
b0 '
04
1"
#110
12
13
1&
1.
1/
b111 )
b111 (
0"
0$
#115
02
03
0&
0.
0/
b1 )
b1 (
05
14
01
10
0-
b111 !
b111 %
b111 '
1,
1"
#120
0"
#125
1.
1/
b11 )
b11 (
1-
b110 !
b110 %
b110 '
0,
1"
#130
0"
#135
0.
0/
b1 )
b1 (
11
00
0-
b101 !
b101 %
b101 '
1,
1"
#140
0"
#145
12
13
1&
1.
1/
b111 )
b111 (
1-
b100 !
b100 %
b100 '
0,
1"
#150
0"
#155
02
03
0&
0.
0/
b1 )
b1 (
15
04
01
10
0-
b11 !
b11 %
b11 '
1,
1"
