Multiplexers/2x1 MUX/mux2to1.v
module mux2to1 (
    input I0,I1,sel,
    output reg y
);
    always @(*) begin
        if (sel) begin
            y=I1;
        end else begin
            y=I0;
        end
    end
endmodule

Multiplexers/2x1 MUX/mux2to1_tb.v
`timescale 1ns/1ns
`include "mux2to1.v"

module mux2to1_tb;
    
    reg I0,I1,sel;
    wire y;
    integer i;

    mux2to1 uut(I0,I1,sel,y);
    initial begin
        $dumpfile("mux2to1.vcd");
        $dumpvars(0,mux2to1_tb);

        $monitor("I0=%d, I1=%d, sel=%d, y=%d",I0,I1,sel,y);

        for (i =0 ;i<8 ;i=i+1 ) begin
            {I0,I1,sel}=i;#5;
        end
    end
endmodule

Multiplexers/2x1 MUX/mux2to1.vcd
$date
	Tue Sep 17 10:56:37 2024
$end
$version
	Icarus Verilog
$end
$timescale
	1ns
$end
$scope module mux2to1_tb $end
$var wire 1 ! y $end
$var reg 1 " I0 $end
$var reg 1 # I1 $end
$var reg 1 $ sel $end
$var integer 32 % i [31:0] $end
$scope module uut $end
$var wire 1 " I0 $end
$var wire 1 # I1 $end
$var wire 1 $ sel $end
$var reg 1 ! y $end
$upscope $end
$upscope $end
$enddefinitions $end
$comment Show the parameter values. $end
$dumpall
$end
#0
$dumpvars
b0 %
0$
0#
0"
0!
$end
#5
1$
b1 %
#10
1#
0$
b10 %
#15
1!
1$
b11 %
#20
1"
0#
0$
b100 %
#25
0!
1$
b101 %
#30
1!
1#
0$
b110 %
#35
1$
b111 %
#40
b1000 %
