JKflipflop/jk.v
module jk (
    input J,K,clk,
    output reg Q,Qn
);
    always @(posedge clk ) begin
        case ({J,K})
            2'b00:
                begin
                    Q=Q;
                    Qn=~Q;
                end
            2'b01: 
                begin
                    Q=0;
                    Qn=~Q;
                end    
            2'b10:
                begin
                    Q=1;
                    Qn=~Q;
                end 
            2'b11:
                begin
                    Q= ~Q;
                    Qn=~Q;
                end 
        endcase
    end
endmodule

JKflipflop/jk_tb.v
`timescale 1ns/1ns
`include "jk.v"

module jk_tb;
    reg clk,J,K;
    wire Q,Qn;

    jk uut(.clk(clk),.J(J),.K(K),.Q(Q),.Qn(Qn));

    initial begin
        $dumpfile("jk.vcd");
        $dumpvars(0,jk_tb);
        clk=0;
        forever begin
            #5 clk=~clk;
        end
    end
    
    initial begin
        $monitor("clk=%0t, J=%d, K=%d, Q=%d, Qn=%d",$time,J,K,Q,Qn);

        J=0;K=0;

        #10 J=1;K=0;
        #10 J=0;K=1;
        #10 J=1;K=1;
        #10 J=0;K=0;
        #10 J=1;K=1;

        #25 $finish;
    end
endmodule

JKflipflop/jk.vcd
$date
	Tue Oct 08 19:23:27 2024
$end
$version
	Icarus Verilog
$end
$timescale
	1ns
$end
$scope module jk_tb $end
$var wire 1 ! Qn $end
$var wire 1 " Q $end
$var reg 1 # J $end
$var reg 1 $ K $end
$var reg 1 % clk $end
$scope module uut $end
$var wire 1 # J $end
$var wire 1 $ K $end
$var wire 1 % clk $end
$var reg 1 " Q $end
$var reg 1 ! Qn $end
$upscope $end
$upscope $end
$enddefinitions $end
$comment Show the parameter values. $end
$dumpall
$end
#0
$dumpvars
0%
0$
0#
x"
x!
$end
#5
1%
#10
0%
1#
#15
0!
1"
1%
#20
0%
1$
0#
#25
1!
0"
1%
#30
0%
1#
#35
0!
1"
1%
#40
0%
0$
0#
#45
1%
#50
0%
1$
1#
#55
1!
0"
1%
#60
0%
#65
0!
1"
1%
#70
0%
#75
1!
0"
1%
