DtoJKflipflop/dtojk.v
module dff (
    input D,clk,
    output reg Q,Qn
);
    always @(posedge clk) begin
        Q<=D;
        Qn<= ~D;
    end
endmodule

module dtojk (
    input J,K,clk,
    output Q,Qn
);
    wire D;
    assign D=(J&~Q)+(~K&Q);
    dff d1(
        .clk(clk),.D(D),.Q(Q),.Qn(Qn)
    );
endmodule

DtoJKflipflop/dtojk_tb.v
`timescale 1ns/1ns
`include "dtojk.v"

module dtojk_tb;
    reg clk,J,K;
    wire Q,Qn;

    dtojk uut(.clk(clk),.J(J),.K(K),.Q(Q),.Qn(Qn));

    initial begin
        $dumpfile("dtojk.vcd");
        $dumpvars(0,dtojk_tb);
        clk=0;
        forever begin
            #5 clk=~clk;
        end
    end
    
    initial begin
        $monitor("clk=%0t, J=%d, K=%d, Q=%d, Qn=%d",$time,J,K,Q,Qn);

        J=0;K=0;

        #10 J=1;K=0;
        #10 J=0;K=1;
        #10 J=1;K=1;
        #10 J=0;K=0;
        #10 J=1;K=1;

        #25 $finish;
    end
endmodule

DtoJKflipflop/dtojk.vcd
$date
	Tue Oct 08 19:13:38 2024
$end
$version
	Icarus Verilog
$end
$timescale
	1ns
$end
$scope module dtojk_tb $end
$var wire 1 ! Qn $end
$var wire 1 " Q $end
$var reg 1 # J $end
$var reg 1 $ K $end
$var reg 1 % clk $end
$scope module uut $end
$var wire 1 # J $end
$var wire 1 $ K $end
$var wire 1 % clk $end
$var wire 1 ! Qn $end
$var wire 1 " Q $end
$var wire 1 & D $end
$scope module d1 $end
$var wire 1 & D $end
$var wire 1 % clk $end
$var reg 1 " Q $end
$var reg 1 ! Qn $end
$upscope $end
$upscope $end
$upscope $end
$enddefinitions $end
$comment Show the parameter values. $end
$dumpall
$end
#0
$dumpvars
x&
0%
0$
0#
x"
x!
$end
#5
1%
#10
0%
1#
#15
1%
#20
0&
0%
1$
0#
#25
1!
0"
1%
#30
1&
0%
1#
#35
0&
0!
1"
1%
#40
1&
0%
0$
0#
#45
1%
#50
0&
0%
1$
1#
#55
1&
1!
0"
1%
#60
0%
#65
0&
0!
1"
1%
#70
0%
#75
1&
1!
0"
1%
