Multiplexers/4x1 MUX/mux4to1.v
module mux2to1 (
    input wire d0,input wire d1,
    input wire sel,output wire seln,
    output wire l,output wire m,
    output wire y         
);
    and g1(l,d1,sel);
    not g2(seln,sel);
    and g3(m,d0,seln);
    or g4(y,l,m);
endmodule

module mux4to1 (
    input wire d0,input wire d1,
    input wire d2,input wire d3,
    input wire s0,input wire s1,
    output wire y 
);
    wire m0, m1;

    mux2to1 mux0 (
        .d0(d0),
        .d1(d1),
        .sel(s0),
        .y(m0)
    );

    mux2to1 mux1 (
        .d0(d2),
        .d1(d3),
        .sel(s0),
        .y(m1)
    );

    mux2to1 mux2 (
        .d0(m0),
        .d1(m1),
        .sel(s1),
        .y(y)
    );
endmodule

Multiplexers/4x1 MUX/mux4to1_tb.v
`timescale 1ns/1ns
`include "mux4to1.v"

module mux4to1_tb;

    reg d0, d1, d2, d3;
    reg s0, s1;
    wire y;
    integer i;
    
    mux4to1 uut (
        .d0(d0),
        .d1(d1),
        .d2(d2),
        .d3(d3),
        .s0(s0),
        .s1(s1),
        .y(y)
    );

    initial begin
        $dumpfile("mux4to1.vcd");
        $dumpvars(0,mux4to1_tb);

        $monitor("d0=%b d1=%b d2=%b d3=%b s1=%b s0=%b y=%b",d0, d1, d2, d3, s1, s0, y);

        for (i =0 ;i<64 ;i=i+1 ) begin
            {d0,d1,d2,d3,s1,s0}=i;#5;
        end
    end
endmodule

Multiplexers/4x1 MUX/mux4to1.vcd
$date
	Tue Sep 17 11:00:12 2024
$end
$version
	Icarus Verilog
$end
$timescale
	1ns
$end
$scope module mux4to1_tb $end
$var wire 1 ! y $end
$var reg 1 " d0 $end
$var reg 1 # d1 $end
$var reg 1 $ d2 $end
$var reg 1 % d3 $end
$var reg 1 & s0 $end
$var reg 1 ' s1 $end
$var integer 32 ( i [31:0] $end
$scope module uut $end
$var wire 1 " d0 $end
$var wire 1 # d1 $end
$var wire 1 $ d2 $end
$var wire 1 % d3 $end
$var wire 1 & s0 $end
$var wire 1 ' s1 $end
$var wire 1 ! y $end
$var wire 1 ) m1 $end
$var wire 1 * m0 $end
$scope module mux0 $end
$var wire 1 " d0 $end
$var wire 1 # d1 $end
$var wire 1 + l $end
$var wire 1 , m $end
$var wire 1 & sel $end
$var wire 1 - seln $end
$var wire 1 * y $end
$upscope $end
$scope module mux1 $end
$var wire 1 $ d0 $end
$var wire 1 % d1 $end
$var wire 1 . l $end
$var wire 1 / m $end
$var wire 1 & sel $end
$var wire 1 0 seln $end
$var wire 1 ) y $end
$upscope $end
$scope module mux2 $end
$var wire 1 * d0 $end
$var wire 1 ) d1 $end
$var wire 1 1 l $end
$var wire 1 2 m $end
$var wire 1 ' sel $end
$var wire 1 3 seln $end
$var wire 1 ! y $end
$upscope $end
$upscope $end
$upscope $end
$enddefinitions $end
$comment Show the parameter values. $end
$dumpall
$end
#0
$dumpvars
13
02
01
10
0/
0.
1-
0,
0+
0*
0)
b0 (
0'
0&
0%
0$
0#
0"
0!
$end
#5
0-
00
1&
b1 (
#10
03
1-
10
1'
0&
b10 (
#15
0-
00
1&
b11 (
#20
13
1-
10
1%
0'
0&
b100 (
#25
1)
0-
1.
00
1&
b101 (
#30
0!
0)
01
03
1-
0.
10
1'
0&
b110 (
#35
1!
11
1)
0-
1.
00
1&
b111 (
#40
0!
1/
01
13
1-
0.
10
1$
0%
0'
0&
b1000 (
#45
0)
0/
0-
00
1&
b1001 (
#50
1!
11
1)
1/
03
1-
10
1'
0&
b1010 (
#55
0!
01
0)
0/
0-
00
1&
b1011 (
#60
1)
1/
13
1-
10
1%
0'
0&
b1100 (
#65
0/
0-
1.
00
1&
b1101 (
#70
1!
1/
11
03
1-
0.
10
1'
0&
b1110 (
#75
0/
0-
1.
00
1&
b1111 (
#80
0!
0)
01
13
1-
0.
10
1#
0$
0%
0'
0&
b10000 (
#85
1!
12
1*
1+
0-
00
1&
b10001 (
#90
0!
02
0*
03
0+
1-
10
1'
0&
b10010 (
#95
1*
1+
0-
00
1&
b10011 (
#100
0*
13
0+
1-
10
1%
0'
0&
b10100 (
#105
1!
12
1*
1)
1+
0-
1.
00
1&
b10101 (
#110
0!
02
0*
0)
01
03
0+
1-
0.
10
1'
0&
b10110 (
#115
1!
11
1*
1)
1+
0-
1.
00
1&
b10111 (
#120
0!
0*
1/
01
13
0+
1-
0.
10
1$
0%
0'
0&
b11000 (
#125
1!
12
0)
1*
0/
1+
0-
00
1&
b11001 (
#130
11
1!
1)
02
0*
1/
03
0+
1-
10
1'
0&
b11010 (
#135
0!
01
0)
1*
0/
1+
0-
00
1&
b11011 (
#140
1)
0*
1/
13
0+
1-
10
1%
0'
0&
b11100 (
#145
1!
12
1*
0/
1+
0-
1.
00
1&
b11101 (
#150
02
0*
1/
11
03
0+
1-
0.
10
1'
0&
b11110 (
#155
1*
0/
1+
0-
1.
00
1&
b11111 (
#160
12
0)
1,
01
13
0+
1-
0.
10
1"
0#
0$
0%
0'
0&
b100000 (
#165
0!
02
0*
0,
0-
00
1&
b100001 (
#170
1*
1,
03
1-
10
1'
0&
b100010 (
#175
0*
0,
0-
00
1&
b100011 (
#180
1!
12
1*
1,
13
1-
10
1%
0'
0&
b100100 (
#185
0!
02
0*
0,
1)
0-
1.
00
1&
b100101 (
#190
1*
0!
1,
0)
01
03
1-
0.
10
1'
0&
b100110 (
#195
1!
0*
11
0,
1)
0-
1.
00
1&
b100111 (
#200
12
1*
1!
1,
1/
01
13
1-
0.
10
1$
0%
0'
0&
b101000 (
#205
0!
02
0*
0)
0,
0/
0-
00
1&
b101001 (
#210
1!
11
1*
1)
1,
1/
03
1-
10
1'
0&
b101010 (
#215
0!
01
0*
0)
0,
0/
0-
00
1&
b101011 (
#220
1!
12
1*
1)
1,
1/
13
1-
10
1%
0'
0&
b101100 (
#225
0!
02
0*
0,
0/
0-
1.
00
1&
b101101 (
#230
1*
1!
1,
1/
11
03
1-
0.
10
1'
0&
b101110 (
#235
0*
0,
0/
0-
1.
00
1&
b101111 (
#240
12
1*
1!
1,
0)
01
13
1-
0.
10
1#
0$
0%
0'
0&
b110000 (
#245
0,
1+
0-
00
1&
b110001 (
#250
0!
02
1,
03
0+
1-
10
1'
0&
b110010 (
#255
0,
1+
0-
00
1&
b110011 (
#260
1!
12
1,
13
0+
1-
10
1%
0'
0&
b110100 (
#265
0,
1)
1+
0-
1.
00
1&
b110101 (
#270
0!
02
1,
0)
01
03
0+
1-
0.
10
1'
0&
b110110 (
#275
1!
11
0,
1)
1+
0-
1.
00
1&
b110111 (
#280
12
1,
1/
01
13
0+
1-
0.
10
1$
0%
0'
0&
b111000 (
#285
0)
0,
0/
1+
0-
00
1&
b111001 (
#290
11
1!
1)
02
1,
1/
03
0+
1-
10
1'
0&
b111010 (
#295
0!
01
0)
0,
0/
1+
0-
00
1&
b111011 (
#300
1!
1)
12
1,
1/
13
0+
1-
10
1%
0'
0&
b111100 (
#305
0,
0/
1+
0-
1.
00
1&
b111101 (
#310
02
1,
1/
11
03
0+
1-
0.
10
1'
0&
b111110 (
#315
0,
0/
1+
0-
1.
00
1&
b111111 (
#320
b1000000 (
