Dlatch/dl.v
module dl (
    input D,en,clk,
    output reg Q,Qn
);
    always @(*) begin
        if (clk) begin
            if (en) begin
                Q<=D;
                Qn<= ~D;
            end
        end
    end
endmodule

Dlatch/dl_tb.v
`timescale 1ns/1ns
`include "dl.v"

module dl_tb;
    reg clk,D,en;
    wire Q,Qn;

    dl uut(.clk(clk),.D(D),.Q(Q),.Qn(Qn),.en(en));

    initial begin
        $dumpfile("dl.vcd");
        $dumpvars(0,dl_tb);
        clk=0;
        forever begin
            #5 clk=~clk;
        end
    end
    
    initial begin
        $monitor("clk=%0t,en=%d ,D=%d, Q=%d, Qn=%d",$time,en,D,Q,Qn);

        D=0;en=0;

        #10 D=1;en=1;
        #10 D=0;en=0;
        #10 D=1;en=0;
        #10 D=0;en=1;
        #10 D=1;en=0;

        #25 $finish;
    end
endmodule

Dlatch/dl.vcd
$date
	Tue Oct 08 19:17:47 2024
$end
$version
	Icarus Verilog
$end
$timescale
	1ns
$end
$scope module dl_tb $end
$var wire 1 ! Qn $end
$var wire 1 " Q $end
$var reg 1 # D $end
$var reg 1 $ clk $end
$var reg 1 % en $end
$scope module uut $end
$var wire 1 # D $end
$var wire 1 $ clk $end
$var wire 1 % en $end
$var reg 1 " Q $end
$var reg 1 ! Qn $end
$upscope $end
$upscope $end
$enddefinitions $end
$comment Show the parameter values. $end
$dumpall
$end
#0
$dumpvars
0%
0$
0#
x"
x!
$end
#5
1$
#10
0$
1%
1#
#15
0!
1"
1$
#20
0$
0%
0#
#25
1$
#30
0$
1#
#35
1$
#40
0$
1%
0#
#45
1!
0"
1$
#50
0$
0%
1#
