4-bit binary to Gray code/BtoG.v
module BtoG (
    input B3, B2, B1 ,B0,
    output G3, G2, G1, G0
);

    /*gate level*/
    assign G3=B3;
    xor g1(G2,B3,B2);
    xor g2(G1,B2,B1);
    xor g3(G0,B1,B0);

    /*data flow
    assign G3=B3;
    assign G2=B3^B2;
    assign G1=B2^B1;
    assign G0=B1^B0;*/

    /*Behavioral Modeling
    always @(*) begin
        G3=B3;
        G2=B3^B2;
        G1=B2^B1;
        G0=B1^B0;
    end*/

endmodule

// module BtoG (
//     input [3:0]B,
//     output reg [3:0]G
// );
//     always @(*) begin
//         G[3]=B[3];
//         G[2]=B[3]^B[2];
//         G[1]=B[2]^B[1];
//         G[0]=B[1]^B[0];
//     end

// endmodule

4-bit binary to Gray code/BtoG_tb.v
`timescale 1ns / 1ns
`include "BtoG.v"

module BtoG_tb;

reg B3, B2, B1 ,B0;
wire G3, G2, G1, G0;
integer i;

BtoG uut(B3, B2, B1 ,B0, G3, G2, G1, G0);

initial begin

    $dumpfile("BtoG_tb.vcd");
    $dumpvars(0, BtoG_tb);

    $monitor("binary code=%d%d%d%d ,gray code=%d%d%d%d",B3,B2,B1,B0,G3, G2, G1, G0);

    for (i=0;i<16 ;i=i+1 ) begin
        {B3,B2,B1,B0}=i; #5;
    end
end

endmodule

// `timescale 1ns / 1ns
// `include "BtoG.v"

// module BtoG_tb;
//     reg [3:0]B;
//     wire [3:0]G;

//     BtoG uut(.B(B),.G(G));
//     initial begin

//     $dumpfile("BtoG_tb.vcd");
//     $dumpvars(0, BtoG_tb);

//     $monitor("binary code=%b ,gray code=%b",B,G);

//     for (B=4'b0000;B< 4'b1111 ;B=B+1 ) begin
//         #5;
//     end
//     $finish;
// end

// endmodule

4-bit binary to Gray code/BtoG_tb.vcd
$date
	Tue Sep 10 14:24:23 2024
$end
$version
	Icarus Verilog
$end
$timescale
	1ns
$end
$scope module BtoG_tb $end
$var wire 1 ! G3 $end
$var wire 1 " G2 $end
$var wire 1 # G1 $end
$var wire 1 $ G0 $end
$var reg 1 % B0 $end
$var reg 1 & B1 $end
$var reg 1 ' B2 $end
$var reg 1 ( B3 $end
$var integer 32 ) i [31:0] $end
$scope module uut $end
$var wire 1 % B0 $end
$var wire 1 & B1 $end
$var wire 1 ' B2 $end
$var wire 1 ( B3 $end
$var wire 1 $ G0 $end
$var wire 1 # G1 $end
$var wire 1 " G2 $end
$var wire 1 ! G3 $end
$upscope $end
$upscope $end
$enddefinitions $end
$comment Show the parameter values. $end
$dumpall
$end
#0
$dumpvars
b0 )
0(
0'
0&
0%
0$
0#
0"
0!
$end
#5
1$
1%
b1 )
#10
1#
1&
0%
b10 )
#15
0$
1%
b11 )
#20
1"
1'
0&
0%
b100 )
#25
1$
1%
b101 )
#30
0#
1&
0%
b110 )
#35
0$
1%
b111 )
#40
1!
1(
0'
0&
0%
b1000 )
#45
1$
1%
b1001 )
#50
1#
1&
0%
b1010 )
#55
0$
1%
b1011 )
#60
0"
1'
0&
0%
b1100 )
#65
1$
1%
b1101 )
#70
0#
1&
0%
b1110 )
#75
0$
1%
b1111 )
#80
b10000 )
