Carry Look Ahead Adder/claa.v
module full_adder (
    input a,b,cin,
    output sum,cout
);
    wire axb;
    
    xor g1(axb,a,b);
    xor g2(sum,axb,cin);

    // and g3(l,a,b);
    // and g4(m,axb,cin);
    // or g5(cout,l,m);
endmodule

module carryGen (
    input A,B,Cin,
    output Cout
);
    wire G,P,l;

    and cg1(G,A,B);
    xor cg2(P,A,B);
    and cg3(l,P,Cin);
    or cg4(Cout,G,l);
endmodule

module claa (
    input A3,A2,A1,A0,B3,B2,B1,B0,Cin,
    output S3,S2,S1,S0,C4,C3,C2,C1
);
    carryGen c1(
        .A(A0),.B(B0),.Cin(Cin),.Cout(C1)
    );
    carryGen c2(
        .A(A1),.B(B1),.Cin(C1),.Cout(C2)
    );
    carryGen c3(
        .A(A2),.B(B2),.Cin(C2),.Cout(C3)
    );
    carryGen c4(
        .A(A3),.B(B3),.Cin(C3),.Cout(C4)
    );
    
    full_adder fl1(
        .a(A0),.b(B0),.cin(Cin),.sum(S0)
    );
    full_adder fl2(
        .a(A1),.b(B1),.cin(C1),.sum(S1)
    );
    full_adder fl3(
        .a(A2),.b(B2),.cin(C2),.sum(S2)
    );
    full_adder fl4(
        .a(A3),.b(B3),.cin(C3),.sum(S3)
    );
endmodule

CLAA/claa_tb.v
`timescale 1ns/1ns
`include "claa.v"

module claa_tb;
    
    reg A3,A2,A1,A0,B3,B2,B1,B0,Cin;
    wire C1,C2,C3,S3,S2,S1,S0;
    integer i,j;

    claa uut (
        .A3(A3),.A2(A2),.A1(A1),.A0(A0),.B3(B3),.B2(B2),.B1(B1),.B0(B0),.Cin(Cin),.C1(C1),.C2(C2),.C3(C3),.C4(C4),.S3(S3),.S2(S2),.S1(S1),.S0(S0)
    );

    initial begin
        $dumpfile("claa.vcd");
        $dumpvars(0,claa_tb);

        $monitor("A3=%b,A2=%b,A1=%b,A0=%b,B3=%b,B2=%b,B1=%b,B0=%b,S3=%b,S2=%b,S1=%b,S0=%b,C4=%b,C3=%b,C2=%b,C1=%b,Cin=%b",A3,A2,A1,A0,B3,B2,B1,B0,S3,S2,S1,S0,C4,C3,C2,C1,Cin);
        Cin=0;
        for (i =0;i<16 ;i=i+1) begin
        {A3,A2,A1,A0}=i;
        for (j =0;j<16 ;j=j+1 ) begin
            {B3,B2,B1,B0}=j;
            #5;
        end
    end
    end
endmodule

Carry Look Ahead Adder/claa.vcd
$date
	Mon Sep 23 18:18:25 2024
$end
$version
	Icarus Verilog
$end
$timescale
	1ns
$end
$scope module claa_tb $end
$var wire 1 ! S3 $end
$var wire 1 " S2 $end
$var wire 1 # S1 $end
$var wire 1 $ S0 $end
$var wire 1 % C4 $end
$var wire 1 & C3 $end
$var wire 1 ' C2 $end
$var wire 1 ( C1 $end
$var reg 1 ) A0 $end
$var reg 1 * A1 $end
$var reg 1 + A2 $end
$var reg 1 , A3 $end
$var reg 1 - B0 $end
$var reg 1 . B1 $end
$var reg 1 / B2 $end
$var reg 1 0 B3 $end
$var reg 1 1 Cin $end
$var integer 32 2 i [31:0] $end
$var integer 32 3 j [31:0] $end
$scope module uut $end
$var wire 1 ) A0 $end
$var wire 1 * A1 $end
$var wire 1 + A2 $end
$var wire 1 , A3 $end
$var wire 1 - B0 $end
$var wire 1 . B1 $end
$var wire 1 / B2 $end
$var wire 1 0 B3 $end
$var wire 1 1 Cin $end
$var wire 1 ! S3 $end
$var wire 1 " S2 $end
$var wire 1 # S1 $end
$var wire 1 $ S0 $end
$var wire 1 % C4 $end
$var wire 1 & C3 $end
$var wire 1 ' C2 $end
$var wire 1 ( C1 $end
$scope module c1 $end
$var wire 1 ) A $end
$var wire 1 - B $end
$var wire 1 1 Cin $end
$var wire 1 ( Cout $end
$var wire 1 4 G $end
$var wire 1 5 P $end
$var wire 1 6 l $end
$upscope $end
$scope module c2 $end
$var wire 1 * A $end
$var wire 1 . B $end
$var wire 1 ( Cin $end
$var wire 1 ' Cout $end
$var wire 1 7 G $end
$var wire 1 8 P $end
$var wire 1 9 l $end
$upscope $end
$scope module c3 $end
$var wire 1 + A $end
$var wire 1 / B $end
$var wire 1 ' Cin $end
$var wire 1 & Cout $end
$var wire 1 : G $end
$var wire 1 ; P $end
$var wire 1 < l $end
$upscope $end
$scope module c4 $end
$var wire 1 , A $end
$var wire 1 0 B $end
$var wire 1 & Cin $end
$var wire 1 % Cout $end
$var wire 1 = G $end
$var wire 1 > P $end
$var wire 1 ? l $end
$upscope $end
$scope module fl1 $end
$var wire 1 ) a $end
$var wire 1 @ axb $end
$var wire 1 - b $end
$var wire 1 1 cin $end
$var wire 1 A cout $end
$var wire 1 $ sum $end
$upscope $end
$scope module fl2 $end
$var wire 1 * a $end
$var wire 1 B axb $end
$var wire 1 . b $end
$var wire 1 ( cin $end
$var wire 1 C cout $end
$var wire 1 # sum $end
$upscope $end
$scope module fl3 $end
$var wire 1 + a $end
$var wire 1 D axb $end
$var wire 1 / b $end
$var wire 1 ' cin $end
$var wire 1 E cout $end
$var wire 1 " sum $end
$upscope $end
$scope module fl4 $end
$var wire 1 , a $end
$var wire 1 F axb $end
$var wire 1 0 b $end
$var wire 1 & cin $end
$var wire 1 G cout $end
$var wire 1 ! sum $end
$upscope $end
$upscope $end
$upscope $end
$enddefinitions $end
$comment Show the parameter values. $end
$dumpall
$end
#0
$dumpvars
zG
0F
zE
0D
zC
0B
zA
0@
0?
0>
0=
0<
0;
0:
09
08
07
06
05
04
b0 3
b0 2
01
00
0/
0.
0-
0,
0+
0*
0)
0(
0'
0&
0%
0$
0#
0"
0!
$end
#5
1$
15
1@
1-
b1 3
#10
1#
0$
18
1B
05
0@
1.
0-
b10 3
#15
1$
15
1@
1-
b11 3
#20
1"
0#
0$
1;
1D
08
0B
05
0@
1/
0.
0-
b100 3
#25
1$
15
1@
1-
b101 3
#30
1#
0$
18
1B
05
0@
1.
0-
b110 3
#35
1$
15
1@
1-
b111 3
#40
1!
0"
0#
0$
1>
1F
0;
0D
08
0B
05
0@
10
0/
0.
0-
b1000 3
#45
1$
15
1@
1-
b1001 3
#50
1#
0$
18
1B
05
0@
1.
0-
b1010 3
#55
1$
15
1@
1-
b1011 3
#60
1"
0#
0$
1;
1D
08
0B
05
0@
1/
0.
0-
b1100 3
#65
1$
15
1@
1-
b1101 3
#70
1#
0$
18
1B
05
0@
1.
0-
b1110 3
#75
1$
15
1@
1-
b1111 3
#80
0!
0"
0#
0>
0F
0;
0D
08
0B
00
0/
0.
0-
1)
b1 2
b0 3
#85
1#
1(
0$
14
05
0@
1-
b1 3
#90
0(
1$
18
1B
04
15
1@
1.
0-
b10 3
#95
1"
1'
19
0#
1(
0$
14
05
0@
1-
b11 3
#100
0!
0&
0'
0<
1"
09
0(
1$
1;
1D
08
0B
04
15
1@
1/
0.
0-
b100 3
#105
1#
1(
0$
14
05
0@
1-
b101 3
#110
0(
1$
18
1B
04
15
1@
1.
0-
b110 3
#115
1!
1&
1<
0"
1'
19
0#
1(
0$
14
05
0@
1-
b111 3
#120
0%
0&
0'
0?
1!
0<
0"
09
0(
1$
1>
1F
0;
0D
08
0B
04
15
1@
10
0/
0.
0-
b1000 3
#125
1#
1(
0$
14
05
0@
1-
b1001 3
#130
0(
1$
18
1B
04
15
1@
1.
0-
b1010 3
#135
1"
1'
19
0#
1(
0$
14
05
0@
1-
b1011 3
#140
0%
0?
1!
0&
0'
0<
1"
09
0(
1$
1;
1D
08
0B
04
15
1@
1/
0.
0-
b1100 3
#145
1#
1(
0$
14
05
0@
1-
b1101 3
#150
0(
1$
18
1B
04
15
1@
1.
0-
b1110 3
#155
1%
1?
0!
1&
1<
0"
1'
19
0#
1(
0$
14
05
0@
1-
b1111 3
#160
0'
0%
0&
09
1#
0?
0!
0<
0"
0(
0>
0F
0;
0D
04
00
0/
0.
0-
1*
0)
b10 2
b0 3
#165
1$
15
1@
1-
b1 3
#170
1"
1'
0#
0$
17
08
0B
05
0@
1.
0-
b10 3
#175
1$
15
1@
1-
b11 3
#180
0'
1#
0$
1;
1D
07
18
1B
05
0@
1/
0.
0-
b100 3
#185
1$
15
1@
1-
b101 3
#190
1!
1&
1<
0"
1'
0#
0$
17
08
0B
05
0@
1.
0-
b110 3
#195
1$
15
1@
1-
b111 3
#200
0%
0&
0?
1!
0<
0'
1#
0$
1>
1F
0;
0D
07
18
1B
05
0@
10
0/
0.
0-
b1000 3
#205
1$
15
1@
1-
b1001 3
#210
1"
1'
0#
0$
17
08
0B
05
0@
1.
0-
b1010 3
#215
1$
15
1@
1-
b1011 3
#220
0'
1#
0$
1;
1D
07
18
1B
05
0@
1/
0.
0-
b1100 3
#225
1$
15
1@
1-
b1101 3
#230
1%
1?
0!
1&
1<
0"
1'
0#
0$
17
08
0B
05
0@
1.
0-
b1110 3
#235
1$
15
1@
1-
b1111 3
#240
0%
0&
0?
0!
0<
0'
1#
0>
0F
0;
0D
07
18
1B
00
0/
0.
0-
1)
b11 2
b0 3
#245
1"
1'
19
0#
1(
0$
14
05
0@
1-
b1 3
#250
09
0(
1$
17
08
0B
04
15
1@
1.
0-
b10 3
#255
1#
1(
0$
14
05
0@
1-
b11 3
#260
0'
0(
1$
1;
1D
07
18
1B
04
15
1@
1/
0.
0-
b100 3
#265
1!
1&
1<
0"
1'
19
0#
1(
0$
14
05
0@
1-
b101 3
#270
09
0(
1$
17
08
0B
04
15
1@
1.
0-
b110 3
#275
1#
1(
0$
14
05
0@
1-
b111 3
#280
0%
0&
0?
1!
0<
0'
0(
1$
1>
1F
0;
0D
07
18
1B
04
15
1@
10
0/
0.
0-
b1000 3
#285
1"
1'
19
0#
1(
0$
14
05
0@
1-
b1001 3
#290
09
0(
1$
17
08
0B
04
15
1@
1.
0-
b1010 3
#295
1#
1(
0$
14
05
0@
1-
b1011 3
#300
0'
0(
1$
1;
1D
07
18
1B
04
15
1@
1/
0.
0-
b1100 3
#305
1%
1?
0!
1&
1<
0"
1'
19
0#
1(
0$
14
05
0@
1-
b1101 3
#310
09
0(
1$
17
08
0B
04
15
1@
1.
0-
b1110 3
#315
1#
1(
0$
14
05
0@
1-
b1111 3
#320
0&
0%
0<
1"
0#
0?
0!
0'
0(
0>
0F
07
04
00
0/
0.
0-
1+
0*
0)
b100 2
b0 3
#325
1$
15
1@
1-
b1 3
#330
1#
0$
18
1B
05
0@
1.
0-
b10 3
#335
1$
15
1@
1-
b11 3
#340
1!
1&
0"
0#
0$
1:
0;
0D
08
0B
05
0@
1/
0.
0-
b100 3
#345
1$
15
1@
1-
b101 3
#350
1#
0$
18
1B
05
0@
1.
0-
b110 3
#355
1$
15
1@
1-
b111 3
#360
0&
1"
0#
0$
1>
1F
0:
1;
1D
08
0B
05
0@
10
0/
0.
0-
b1000 3
#365
1$
15
1@
1-
b1001 3
#370
1#
0$
18
1B
05
0@
1.
0-
b1010 3
#375
1$
15
1@
1-
b1011 3
#380
1%
1?
0!
1&
0"
0#
0$
1:
0;
0D
08
0B
05
0@
1/
0.
0-
b1100 3
#385
1$
15
1@
1-
b1101 3
#390
1#
0$
18
1B
05
0@
1.
0-
b1110 3
#395
1$
15
1@
1-
b1111 3
#400
0%
0?
0&
1"
0#
0>
0F
0:
1;
1D
08
0B
00
0/
0.
0-
1)
b101 2
b0 3
#405
1#
1(
0$
14
05
0@
1-
b1 3
#410
0(
1$
18
1B
04
15
1@
1.
0-
b10 3
#415
1!
1&
1<
0"
1'
19
0#
1(
0$
14
05
0@
1-
b11 3
#420
0'
0<
0"
09
0(
1$
1:
0;
0D
08
0B
04
15
1@
1/
0.
0-
b100 3
#425
1#
1(
0$
14
05
0@
1-
b101 3
#430
0(
1$
18
1B
04
15
1@
1.
0-
b110 3
#435
1"
1'
19
0#
1(
0$
14
05
0@
1-
b111 3
#440
0&
0%
0'
0?
1!
0<
1"
09
0(
1$
1>
1F
0:
1;
1D
08
0B
04
15
1@
10
0/
0.
0-
b1000 3
#445
1#
1(
0$
14
05
0@
1-
b1001 3
#450
0(
1$
18
1B
04
15
1@
1.
0-
b1010 3
#455
1%
1?
0!
1&
1<
0"
1'
19
0#
1(
0$
14
05
0@
1-
b1011 3
#460
0'
0<
0"
09
0(
1$
1:
0;
0D
08
0B
04
15
1@
1/
0.
0-
b1100 3
#465
1#
1(
0$
14
05
0@
1-
b1101 3
#470
0(
1$
18
1B
04
15
1@
1.
0-
b1110 3
#475
1"
1'
19
0#
1(
0$
14
05
0@
1-
b1111 3
#480
0&
0'
0%
09
1#
0?
0!
0<
1"
0(
0>
0F
0:
1;
1D
04
00
0/
0.
0-
1*
0)
b110 2
b0 3
#485
1$
15
1@
1-
b1 3
#490
1!
1&
1<
0"
1'
0#
0$
17
08
0B
05
0@
1.
0-
b10 3
#495
1$
15
1@
1-
b11 3
#500
0<
0'
1#
0$
1:
0;
0D
07
18
1B
05
0@
1/
0.
0-
b100 3
#505
1$
15
1@
1-
b101 3
#510
1"
1'
0#
0$
17
08
0B
05
0@
1.
0-
b110 3
#515
1$
15
1@
1-
b111 3
#520
0&
0'
1#
0$
1>
1F
0:
1;
1D
07
18
1B
05
0@
10
0/
0.
0-
b1000 3
#525
1$
15
1@
1-
b1001 3
#530
1%
1?
0!
1&
1<
0"
1'
0#
0$
17
08
0B
05
0@
1.
0-
b1010 3
#535
1$
15
1@
1-
b1011 3
#540
0<
0'
1#
0$
1:
0;
0D
07
18
1B
05
0@
1/
0.
0-
b1100 3
#545
1$
15
1@
1-
b1101 3
#550
1"
1'
0#
0$
17
08
0B
05
0@
1.
0-
b1110 3
#555
1$
15
1@
1-
b1111 3
#560
0%
0?
0&
0'
1#
0>
0F
0:
1;
1D
07
18
1B
00
0/
0.
0-
1)
b111 2
b0 3
#565
1!
1&
1<
0"
1'
19
0#
1(
0$
14
05
0@
1-
b1 3
#570
09
0(
1$
17
08
0B
04
15
1@
1.
0-
b10 3
#575
1#
1(
0$
14
05
0@
1-
b11 3
#580
0<
0'
0(
1$
1:
0;
0D
07
18
1B
04
15
1@
1/
0.
0-
b100 3
#585
1"
1'
19
0#
1(
0$
14
05
0@
1-
b101 3
#590
09
0(
1$
17
08
0B
04
15
1@
1.
0-
b110 3
#595
1#
1(
0$
14
05
0@
1-
b111 3
#600
0&
0'
0(
1$
1>
1F
0:
1;
1D
07
18
1B
04
15
1@
10
0/
0.
0-
b1000 3
#605
1%
1?
0!
1&
1<
0"
1'
19
0#
1(
0$
14
05
0@
1-
b1001 3
#610
09
0(
1$
17
08
0B
04
15
1@
1.
0-
b1010 3
#615
1#
1(
0$
14
05
0@
1-
b1011 3
#620
0<
0'
0(
1$
1:
0;
0D
07
18
1B
04
15
1@
1/
0.
0-
b1100 3
#625
1"
1'
19
0#
1(
0$
14
05
0@
1-
b1101 3
#630
09
0(
1$
17
08
0B
04
15
1@
1.
0-
b1110 3
#635
1#
1(
0$
14
05
0@
1-
b1111 3
#640
0%
0?
1!
0"
0#
0&
0'
0(
0:
07
04
00
0/
0.
0-
1,
0+
0*
0)
b1000 2
b0 3
#645
1$
15
1@
1-
b1 3
#650
1#
0$
18
1B
05
0@
1.
0-
b10 3
#655
1$
15
1@
1-
b11 3
#660
1"
0#
0$
1;
1D
08
0B
05
0@
1/
0.
0-
b100 3
#665
1$
15
1@
1-
b101 3
#670
1#
0$
18
1B
05
0@
1.
0-
b110 3
#675
1$
15
1@
1-
b111 3
#680
1%
0!
0"
0#
0$
1=
0>
0F
0;
0D
08
0B
05
0@
10
0/
0.
0-
b1000 3
#685
1$
15
1@
1-
b1001 3
#690
1#
0$
18
1B
05
0@
1.
0-
b1010 3
#695
1$
15
1@
1-
b1011 3
#700
1"
0#
0$
1;
1D
08
0B
05
0@
1/
0.
0-
b1100 3
#705
1$
15
1@
1-
b1101 3
#710
1#
0$
18
1B
05
0@
1.
0-
b1110 3
#715
1$
15
1@
1-
b1111 3
#720
0%
1!
0"
0#
0=
1>
1F
0;
0D
08
0B
00
0/
0.
0-
1)
b1001 2
b0 3
#725
1#
1(
0$
14
05
0@
1-
b1 3
#730
0(
1$
18
1B
04
15
1@
1.
0-
b10 3
#735
1"
1'
19
0#
1(
0$
14
05
0@
1-
b11 3
#740
0%
0?
1!
0&
0'
0<
1"
09
0(
1$
1;
1D
08
0B
04
15
1@
1/
0.
0-
b100 3
#745
1#
1(
0$
14
05
0@
1-
b101 3
#750
0(
1$
18
1B
04
15
1@
1.
0-
b110 3
#755
1%
1?
0!
1&
1<
0"
1'
19
0#
1(
0$
14
05
0@
1-
b111 3
#760
0&
0'
0?
0!
0<
0"
09
0(
1$
1=
0>
0F
0;
0D
08
0B
04
15
1@
10
0/
0.
0-
b1000 3
#765
1#
1(
0$
14
05
0@
1-
b1001 3
#770
0(
1$
18
1B
04
15
1@
1.
0-
b1010 3
#775
1"
1'
19
0#
1(
0$
14
05
0@
1-
b1011 3
#780
0!
0&
0'
0<
1"
09
0(
1$
1;
1D
08
0B
04
15
1@
1/
0.
0-
b1100 3
#785
1#
1(
0$
14
05
0@
1-
b1101 3
#790
0(
1$
18
1B
04
15
1@
1.
0-
b1110 3
#795
1!
1&
1<
0"
1'
19
0#
1(
0$
14
05
0@
1-
b1111 3
#800
0%
0'
0&
09
1#
0?
1!
0<
0"
0(
0=
1>
1F
0;
0D
04
00
0/
0.
0-
1*
0)
b1010 2
b0 3
#805
1$
15
1@
1-
b1 3
#810
1"
1'
0#
0$
17
08
0B
05
0@
1.
0-
b10 3
#815
1$
15
1@
1-
b11 3
#820
0'
1#
0$
1;
1D
07
18
1B
05
0@
1/
0.
0-
b100 3
#825
1$
15
1@
1-
b101 3
#830
1%
1?
0!
1&
1<
0"
1'
0#
0$
17
08
0B
05
0@
1.
0-
b110 3
#835
1$
15
1@
1-
b111 3
#840
0&
0?
0!
0<
0'
1#
0$
1=
0>
0F
0;
0D
07
18
1B
05
0@
10
0/
0.
0-
b1000 3
#845
1$
15
1@
1-
b1001 3
#850
1"
1'
0#
0$
17
08
0B
05
0@
1.
0-
b1010 3
#855
1$
15
1@
1-
b1011 3
#860
0'
1#
0$
1;
1D
07
18
1B
05
0@
1/
0.
0-
b1100 3
#865
1$
15
1@
1-
b1101 3
#870
1!
1&
1<
0"
1'
0#
0$
17
08
0B
05
0@
1.
0-
b1110 3
#875
1$
15
1@
1-
b1111 3
#880
0%
0&
0?
1!
0<
0'
1#
0=
1>
1F
0;
0D
07
18
1B
00
0/
0.
0-
1)
b1011 2
b0 3
#885
1"
1'
19
0#
1(
0$
14
05
0@
1-
b1 3
#890
09
0(
1$
17
08
0B
04
15
1@
1.
0-
b10 3
#895
1#
1(
0$
14
05
0@
1-
b11 3
#900
0'
0(
1$
1;
1D
07
18
1B
04
15
1@
1/
0.
0-
b100 3
#905
1%
1?
0!
1&
1<
0"
1'
19
0#
1(
0$
14
05
0@
1-
b101 3
#910
09
0(
1$
17
08
0B
04
15
1@
1.
0-
b110 3
#915
1#
1(
0$
14
05
0@
1-
b111 3
#920
0&
0?
0!
0<
0'
0(
1$
1=
0>
0F
0;
0D
07
18
1B
04
15
1@
10
0/
0.
0-
b1000 3
#925
1"
1'
19
0#
1(
0$
14
05
0@
1-
b1001 3
#930
09
0(
1$
17
08
0B
04
15
1@
1.
0-
b1010 3
#935
1#
1(
0$
14
05
0@
1-
b1011 3
#940
0'
0(
1$
1;
1D
07
18
1B
04
15
1@
1/
0.
0-
b1100 3
#945
1!
1&
1<
0"
1'
19
0#
1(
0$
14
05
0@
1-
b1101 3
#950
09
0(
1$
17
08
0B
04
15
1@
1.
0-
b1110 3
#955
1#
1(
0$
14
05
0@
1-
b1111 3
#960
0%
0&
0<
1"
0#
0?
1!
0'
0(
0=
1>
1F
07
04
00
0/
0.
0-
1+
0*
0)
b1100 2
b0 3
#965
1$
15
1@
1-
b1 3
#970
1#
0$
18
1B
05
0@
1.
0-
b10 3
#975
1$
15
1@
1-
b11 3
#980
1%
1?
0!
1&
0"
0#
0$
1:
0;
0D
08
0B
05
0@
1/
0.
0-
b100 3
#985
1$
15
1@
1-
b101 3
#990
1#
0$
18
1B
05
0@
1.
0-
b110 3
#995
1$
15
1@
1-
b111 3
#1000
0?
0&
1"
0#
0$
1=
0>
0F
0:
1;
1D
08
0B
05
0@
10
0/
0.
0-
b1000 3
#1005
1$
15
1@
1-
b1001 3
#1010
1#
0$
18
1B
05
0@
1.
0-
b1010 3
#1015
1$
15
1@
1-
b1011 3
#1020
1!
1&
0"
0#
0$
1:
0;
0D
08
0B
05
0@
1/
0.
0-
b1100 3
#1025
1$
15
1@
1-
b1101 3
#1030
1#
0$
18
1B
05
0@
1.
0-
b1110 3
#1035
1$
15
1@
1-
b1111 3
#1040
0%
0&
1"
0#
0=
1>
1F
0:
1;
1D
08
0B
00
0/
0.
0-
1)
b1101 2
b0 3
#1045
1#
1(
0$
14
05
0@
1-
b1 3
#1050
0(
1$
18
1B
04
15
1@
1.
0-
b10 3
#1055
1%
1?
0!
1&
1<
0"
1'
19
0#
1(
0$
14
05
0@
1-
b11 3
#1060
0'
0<
0"
09
0(
1$
1:
0;
0D
08
0B
04
15
1@
1/
0.
0-
b100 3
#1065
1#
1(
0$
14
05
0@
1-
b101 3
#1070
0(
1$
18
1B
04
15
1@
1.
0-
b110 3
#1075
1"
1'
19
0#
1(
0$
14
05
0@
1-
b111 3
#1080
0&
0'
0?
0!
0<
1"
09
0(
1$
1=
0>
0F
0:
1;
1D
08
0B
04
15
1@
10
0/
0.
0-
b1000 3
#1085
1#
1(
0$
14
05
0@
1-
b1001 3
#1090
0(
1$
18
1B
04
15
1@
1.
0-
b1010 3
#1095
1!
1&
1<
0"
1'
19
0#
1(
0$
14
05
0@
1-
b1011 3
#1100
0'
0<
0"
09
0(
1$
1:
0;
0D
08
0B
04
15
1@
1/
0.
0-
b1100 3
#1105
1#
1(
0$
14
05
0@
1-
b1101 3
#1110
0(
1$
18
1B
04
15
1@
1.
0-
b1110 3
#1115
1"
1'
19
0#
1(
0$
14
05
0@
1-
b1111 3
#1120
0%
0&
0'
09
1#
0?
1!
0<
1"
0(
0=
1>
1F
0:
1;
1D
04
00
0/
0.
0-
1*
0)
b1110 2
b0 3
#1125
1$
15
1@
1-
b1 3
#1130
1%
1?
0!
1&
1<
0"
1'
0#
0$
17
08
0B
05
0@
1.
0-
b10 3
#1135
1$
15
1@
1-
b11 3
#1140
0<
0'
1#
0$
1:
0;
0D
07
18
1B
05
0@
1/
0.
0-
b100 3
#1145
1$
15
1@
1-
b101 3
#1150
1"
1'
0#
0$
17
08
0B
05
0@
1.
0-
b110 3
#1155
1$
15
1@
1-
b111 3
#1160
0?
0&
0'
1#
0$
1=
0>
0F
0:
1;
1D
07
18
1B
05
0@
10
0/
0.
0-
b1000 3
#1165
1$
15
1@
1-
b1001 3
#1170
1!
1&
1<
0"
1'
0#
0$
17
08
0B
05
0@
1.
0-
b1010 3
#1175
1$
15
1@
1-
b1011 3
#1180
0<
0'
1#
0$
1:
0;
0D
07
18
1B
05
0@
1/
0.
0-
b1100 3
#1185
1$
15
1@
1-
b1101 3
#1190
1"
1'
0#
0$
17
08
0B
05
0@
1.
0-
b1110 3
#1195
1$
15
1@
1-
b1111 3
#1200
0%
0&
0'
1#
0=
1>
1F
0:
1;
1D
07
18
1B
00
0/
0.
0-
1)
b1111 2
b0 3
#1205
1%
1?
0!
1&
1<
0"
1'
19
0#
1(
0$
14
05
0@
1-
b1 3
#1210
09
0(
1$
17
08
0B
04
15
1@
1.
0-
b10 3
#1215
1#
1(
0$
14
05
0@
1-
b11 3
#1220
0<
0'
0(
1$
1:
0;
0D
07
18
1B
04
15
1@
1/
0.
0-
b100 3
#1225
1"
1'
19
0#
1(
0$
14
05
0@
1-
b101 3
#1230
09
0(
1$
17
08
0B
04
15
1@
1.
0-
b110 3
#1235
1#
1(
0$
14
05
0@
1-
b111 3
#1240
0?
0&
0'
0(
1$
1=
0>
0F
0:
1;
1D
07
18
1B
04
15
1@
10
0/
0.
0-
b1000 3
#1245
1!
1&
1<
0"
1'
19
0#
1(
0$
14
05
0@
1-
b1001 3
#1250
09
0(
1$
17
08
0B
04
15
1@
1.
0-
b1010 3
#1255
1#
1(
0$
14
05
0@
1-
b1011 3
#1260
0<
0'
0(
1$
1:
0;
0D
07
18
1B
04
15
1@
1/
0.
0-
b1100 3
#1265
1"
1'
19
0#
1(
0$
14
05
0@
1-
b1101 3
#1270
09
0(
1$
17
08
0B
04
15
1@
1.
0-
b1110 3
#1275
1#
1(
0$
14
05
0@
1-
b1111 3
#1280
b10000 2
b10000 3
