SRlatch/sr.v
module sr (
    input S,R,en,clk,
    output reg Q,Qn
);
    always @(*) begin
        if (clk) begin
            if (en) begin
                if (S&&~R) begin
                    Q<=1;
                    Qn<=0;
                end
                if (~S&&R) begin
                    Q<=0;
                    Qn<=1;
                end
                if (S&&R) begin
                    $finish;
                end
            end
        end
    end
endmodule

SRlatch/sr_tb.v
`timescale 1ns/1ns
`include "sr.v"

module sr_tb;
    reg clk,S,R,en;
    wire Q,Qn;

    sr uut(.clk(clk),.S(S),.R(R),.Q(Q),.Qn(Qn),.en(en));

    initial begin
        $dumpfile("sr.vcd");
        $dumpvars(0,sr_tb);
        clk=0;
        forever begin
            #5 clk=~clk;
        end
    end
    
    initial begin
        $monitor("clk=%0t,en=%d ,S=%d ,R=%d ,Q=%d, Qn=%d",$time,en,S,R,Q,Qn);

        S=0;R=0;en=1;

        #10 S=0;R=1;en=1;
        #10 S=1;R=0;en=0;
        #10 S=0;R=0;en=1;
        #10 S=1;R=0;en=1;
        #10 S=0;R=0;en=1;

        #25 $finish;
    end
endmodule

SRlatch/sr.vcd
$date
	Tue Oct 08 19:26:57 2024
$end
$version
	Icarus Verilog
$end
$timescale
	1ns
$end
$scope module sr_tb $end
$var wire 1 ! Qn $end
$var wire 1 " Q $end
$var reg 1 # R $end
$var reg 1 $ S $end
$var reg 1 % clk $end
$var reg 1 & en $end
$scope module uut $end
$var wire 1 # R $end
$var wire 1 $ S $end
$var wire 1 % clk $end
$var wire 1 & en $end
$var reg 1 " Q $end
$var reg 1 ! Qn $end
$upscope $end
$upscope $end
$enddefinitions $end
$comment Show the parameter values. $end
$dumpall
$end
#0
$dumpvars
1&
0%
0$
0#
x"
x!
$end
#5
1%
#10
0%
1#
#15
1!
0"
1%
#20
0%
0&
0#
1$
#25
1%
#30
0%
1&
0$
#35
1%
#40
0%
1$
#45
0!
1"
1%
#50
0%
0$
